May61bo/Download_the_song_kugou.py
May61bo/__init__.py
May61bo/may61bo.py
May61bo-0.0.4.dist-info/LICENSE
May61bo-0.0.4.dist-info/METADATA
May61bo-0.0.4.dist-info/WHEEL
May61bo-0.0.4.dist-info/top_level.txt
May61bo-0.0.4.dist-info/RECORD
