Metadata-Version: 2.1
Name: May61bo
Version: 0.0.4
Summary: This project is only used to test whether it can be uploaded, and there is no function for the time being
Author: 61bo
Author-email: 1926229516@qq.com
License-File: LICENSE
